LICENSE
README.md
setup.cfg
setup.py
snowflake_to_slack/__init__.py
snowflake_to_slack/cli.py
snowflake_to_slack/message.py
snowflake_to_slack/snowflake.py
snowflake_to_slack.egg-info/PKG-INFO
snowflake_to_slack.egg-info/SOURCES.txt
snowflake_to_slack.egg-info/dependency_links.txt
snowflake_to_slack.egg-info/entry_points.txt
snowflake_to_slack.egg-info/requires.txt
snowflake_to_slack.egg-info/top_level.txt