Metadata-Version: 2.1
Name: snowflake-to-slack
Version: 1.0.0
Summary: Send Slack messages spiced with data from Snowflake.
Home-page: https://github.com/offbi/snowflake-to-slack
Author: Radek Tomšej
Author-email: radek@tomsej.cz
License: MIT
Platform: UNKNOWN
Classifier: License :: OSI Approved :: MIT License
Classifier: Programming Language :: Python :: 3
Classifier: Programming Language :: Python :: 3 :: Only
Classifier: Programming Language :: Python :: 3.7
Classifier: Programming Language :: Python :: 3.8
Classifier: Programming Language :: Python :: 3.9
Classifier: Programming Language :: Python :: Implementation :: PyPy
Requires-Python: >=3.7.1
